[
    {
        "date": "2026-06-27T23:56:38.073089",
        "team1": "BOOM Esports",
        "team2": "Team Spirit",
        "winner": 1,
        "score": "2-1",
        "format": "BO3",
        "stage": "CQ D'or TI",
        "deltas": {
            "team1": 3,
            "team2": -3
        },
        "games": [
            {
                "winner": 1,
                "k1": 32,
                "k2": 19
            },
            {
                "winner": 2,
                "k1": 9,
                "k2": 26
            },
            {
                "winner": 1,
                "k1": 28,
                "k2": 22
            }
        ]
    },
    {
        "date": "2026-06-27T23:56:38.073175",
        "team1": "Invictus Gaming",
        "team2": "Talents Ascent",
        "winner": 2,
        "score": "1-2",
        "format": "BO3",
        "stage": "CQ D'or TI",
        "deltas": {
            "team1": -3,
            "team2": 3
        },
        "games": [
            {
                "winner": 2,
                "k1": 8,
                "k2": 23
            },
            {
                "winner": 1,
                "k1": 33,
                "k2": 26
            },
            {
                "winner": 2,
                "k1": 17,
                "k2": 33
            }
        ]
    },
    {
        "date": "2026-06-27T23:56:38.073202",
        "team1": "Frozen Talants",
        "team2": "Vitality (N)",
        "winner": 2,
        "score": "1-2",
        "format": "BO3",
        "stage": "CQ D'or TI",
        "deltas": {
            "team1": -3,
            "team2": 3
        },
        "games": [
            {
                "winner": 2,
                "k1": 23,
                "k2": 35
            },
            {
                "winner": 1,
                "k1": 34,
                "k2": 22
            },
            {
                "winner": 2,
                "k1": 33,
                "k2": 36
            }
        ]
    },
    {
        "date": "2026-06-27T23:56:38.073225",
        "team1": "Team Liquid",
        "team2": "Dream Destroyers",
        "winner": 2,
        "score": "1-2",
        "format": "BO3",
        "stage": "CQ D'or TI",
        "deltas": {
            "team1": -4,
            "team2": 4
        },
        "games": [
            {
                "winner": 2,
                "k1": 17,
                "k2": 22
            },
            {
                "winner": 1,
                "k1": 36,
                "k2": 35
            },
            {
                "winner": 2,
                "k1": 10,
                "k2": 24
            }
        ]
    },
    {
        "date": "2026-06-27T23:56:38.073247",
        "team1": "Xtreme Gaming",
        "team2": "Aurora Gaming",
        "winner": 2,
        "score": "1-2",
        "format": "BO3",
        "stage": "CQ D'or TI",
        "deltas": {
            "team1": -3,
            "team2": 3
        },
        "games": [
            {
                "winner": 2,
                "k1": 19,
                "k2": 23
            },
            {
                "winner": 1,
                "k1": 33,
                "k2": 30
            },
            {
                "winner": 2,
                "k1": 20,
                "k2": 25
            }
        ]
    },
    {
        "date": "2026-06-27T23:56:38.073268",
        "team1": "PARIVISION",
        "team2": "BC.Game",
        "winner": 2,
        "score": "0-2",
        "format": "BO3",
        "stage": "CQ D'or TI",
        "deltas": {
            "team1": -3,
            "team2": 3
        },
        "games": [
            {
                "winner": 2,
                "k1": 2,
                "k2": 21
            },
            {
                "winner": 2,
                "k1": 4,
                "k2": 35
            }
        ]
    },
    {
        "date": "2026-06-27T23:56:38.073290",
        "team1": "BoomBoys",
        "team2": "RandomSS SQ",
        "winner": 2,
        "score": "0-2",
        "format": "BO3",
        "stage": "CQ D'or TI",
        "deltas": {
            "team1": -2,
            "team2": 2
        },
        "games": [
            {
                "winner": 2,
                "k1": 2,
                "k2": 20
            },
            {
                "winner": 2,
                "k1": 19,
                "k2": 20
            }
        ]
    },
    {
        "date": "2026-06-27T23:56:38.073310",
        "team1": "FaZe (Y)",
        "team2": "Team Yandex",
        "winner": 1,
        "score": "2-0",
        "format": "BO3",
        "stage": "CQ D'or TI",
        "deltas": {
            "team1": 3,
            "team2": -3
        },
        "games": [
            {
                "winner": 1,
                "k1": 37,
                "k2": 30
            },
            {
                "winner": 1,
                "k1": 24,
                "k2": 10
            }
        ]
    },
    {
        "date": "2026-06-27T23:56:38.073331",
        "team1": "BOOM Esports",
        "team2": "Talents Ascent",
        "winner": 2,
        "score": "0-2",
        "format": "BO3",
        "stage": "CQ D'or TI",
        "deltas": {
            "team1": -3,
            "team2": 3
        },
        "games": [
            {
                "winner": 2,
                "k1": 24,
                "k2": 25
            },
            {
                "winner": 2,
                "k1": 6,
                "k2": 24
            }
        ]
    },
    {
        "date": "2026-06-27T23:56:38.073352",
        "team1": "Vitality (N)",
        "team2": "Dream Destroyers",
        "winner": 1,
        "score": "2-1",
        "format": "BO3",
        "stage": "CQ D'or TI",
        "deltas": {
            "team1": 3,
            "team2": -3
        },
        "games": [
            {
                "winner": 1,
                "k1": 23,
                "k2": 5
            },
            {
                "winner": 2,
                "k1": 16,
                "k2": 30
            },
            {
                "winner": 1,
                "k1": 34,
                "k2": 24
            }
        ]
    },
    {
        "date": "2026-06-27T23:56:38.073373",
        "team1": "Aurora Gaming",
        "team2": "BC.Game",
        "winner": 1,
        "score": "2-1",
        "format": "BO3",
        "stage": "CQ D'or TI",
        "deltas": {
            "team1": 3,
            "team2": -3
        },
        "games": [
            {
                "winner": 2,
                "k1": 25,
                "k2": 33
            },
            {
                "winner": 1,
                "k1": 25,
                "k2": 2
            },
            {
                "winner": 1,
                "k1": 27,
                "k2": 24
            }
        ]
    },
    {
        "date": "2026-06-27T23:56:38.073392",
        "team1": "RandomSS SQ",
        "team2": "FaZe (Y)",
        "winner": 2,
        "score": "0-2",
        "format": "BO3",
        "stage": "CQ D'or TI",
        "deltas": {
            "team1": -3,
            "team2": 3
        },
        "games": [
            {
                "winner": 2,
                "k1": 10,
                "k2": 30
            },
            {
                "winner": 2,
                "k1": 11,
                "k2": 21
            }
        ]
    },
    {
        "date": "2026-06-27T23:56:38.073415",
        "team1": "Talents Ascent",
        "team2": "Vitality (N)",
        "winner": 2,
        "score": "1-2",
        "format": "BO3",
        "stage": "CQ D'or TI",
        "deltas": {
            "team1": -4,
            "team2": 4
        },
        "games": [
            {
                "winner": 1,
                "k1": 26,
                "k2": 19
            },
            {
                "winner": 2,
                "k1": 21,
                "k2": 32
            },
            {
                "winner": 2,
                "k1": 2,
                "k2": 35
            }
        ]
    },
    {
        "date": "2026-06-27T23:56:38.073441",
        "team1": "Aurora Gaming",
        "team2": "FaZe (Y)",
        "winner": 1,
        "score": "2-0",
        "format": "BO3",
        "stage": "CQ D'or TI",
        "deltas": {
            "team1": 3,
            "team2": -3
        },
        "games": [
            {
                "winner": 1,
                "k1": 26,
                "k2": 16
            },
            {
                "winner": 1,
                "k1": 23,
                "k2": 22
            }
        ]
    }
]