{
    "BC.Game": 1811,
    "RandomSS SQ": 1871,
    "Team Falcons (P)": 1947,
    "beastcoast": 2069,
    "BOOM Esports": 1842,
    "Aurora Gaming": 1864,
    "Dream Destroyers": 1781,
    "Team Yandex": 1781,
    "FaZe (Y)": 1917,
    "Talents Ascent": 1880,
    "Xtreme Gaming": 1811,
    "Invictus Gaming": 1849,
    "Hokori Skraffka": 1931,
    "Vitality (N)": 1865,
    "Gaimin Gladiators (O)": 1899,
    "Team Spirit": 1850,
    "1win (L)": 1925,
    "PARIVISION": 1778,
    "T1": 1726,
    "Natus Vincere": 1728,
    "Team Liquid": 1852,
    "BoomBoys": 1713,
    "Team Secret": 1689,
    "Frozen Talants": 1783,
    "MOUZ": 1711,
    "LGD": 1719,
    "WW": 1723,
    "Virtus.pro": 1612,
    "MayBe": 1870,
    "Vici Gaming": 1890,
    "ex-lapared": 1533,
    "Ramzes's Team": 1877
}